pearson_pdf/__init__.py
pearson_pdf/__main__.py
pearson_pdf/py.typed
pearson_pdf-1.4.0.dist-info/entry_points.txt
pearson_pdf-1.4.0.dist-info/LICENSE
pearson_pdf-1.4.0.dist-info/WHEEL
pearson_pdf-1.4.0.dist-info/METADATA
pearson_pdf-1.4.0.dist-info/RECORD
