Metadata-Version: 2.1
Name: pearson-pdf
Version: 1.4.0
Summary: Tool to download Pearson books as PDFs.
Home-page: https://github.com/jyooru/pearson-pdf
License: MIT
Keywords: pearson,ebook,pdf
Author: Joel
Author-email: joel@joel.tokyo
Requires-Python: >=3.7,<4.0
Classifier: Development Status :: 5 - Production/Stable
Classifier: Environment :: Console
Classifier: Intended Audience :: End Users/Desktop
Classifier: License :: OSI Approved :: MIT License
Classifier: Operating System :: OS Independent
Classifier: Programming Language :: Python :: 3
Classifier: Programming Language :: Python :: 3.10
Classifier: Programming Language :: Python :: 3.7
Classifier: Programming Language :: Python :: 3.8
Classifier: Programming Language :: Python :: 3.9
Requires-Dist: Pillow (>=8.3.2,<10.0.0)
Requires-Dist: requests (>=2.26.0,<3.0.0)
Project-URL: Repository, https://github.com/jyooru/pearson-pdf
